Workbook

Sheet Raw_Data
A1: .
B2: Metric | C2: Unit | D2: 2024 | E2: 2025
B3: Total Revenue | C3: KZT million | D3: 2532156 | E3: 4046074
B4: Payments Revenue | C4: KZT million | D4: 587097 | E4: 658726
B5: Marketplace Revenue | C5: KZT million | D5: 732943 | E5: 1931472
B6: Fintech Revenue | C6: KZT million | D6: 1281827 | E6: 1542934
B7: Consolidated Net Income | C7: KZT million | D7: 1056834 | E7: 1067707
B9: Payments TPV | C9: KZT million | D9: 37229000 | E9: 44219000
B10: Marketplace GMV | C10: KZT million | D10: 5975000 | E10: 6657000
B11: Fintech TFV | C11: KZT million | D11: 10305000 | E11: 11652000
B13: Payments Active Consumers | C13: million users | D13: 13.6 | E13: 14.6
B14: Marketplace Active Consumers | C14: million users | D14: 8.1 | E14: 8.8
B15: Fintech Consumers (Loans) | C15: million users | D15: 6.4 | E15: 6.3
B17: Hepsiburada Marketplace Revenue | C17: KZT million | D17: 0 | E17: =302921+638164+54269 -> 995354
B18: Cost of Goods & Services (COGS) | C18: KZT million | D18: 303858 | E18: 1179141

Sheet Analysis
C2: 2024 | D2: 2025 | E2: YoY
B3: YoY Growth
B4: Total Revenue | D4: =(Raw_Data!E3 / Raw_Data!D3) - 1 -> 0.59787707
B5: Payments Revenue | D5: =(Raw_Data!E4 / Raw_Data!D4) - 1 -> 0.12200539
B6: Marketplace Revenue | D6: =(Raw_Data!E5 / Raw_Data!D5) - 1 -> 1.6352281
B7: Fintech Revenue | D7: =(Raw_Data!E6 / Raw_Data!D6) - 1 -> 0.2036991
B8: Net Income | D8: =(Raw_Data!E7 / Raw_Data!D7) - 1 -> 0.010288276
B10: Revenue Mix
B11: Payments | C11: =Raw_Data!D4 / SUM(Raw_Data!D$4:D$6) -> 0.22564451 | D11: =Raw_Data!E4 / SUM(Raw_Data!E$4:E$6) -> 0.15937696
B12: Marketplace | C12: =Raw_Data!D5 / SUM(Raw_Data!D$4:D$6) -> 0.28169887 | D12: =Raw_Data!E5 / SUM(Raw_Data!E$4:E$6) -> 0.46731438
B13: Fintech | C13: =Raw_Data!D6 / SUM(Raw_Data!D$4:D$6) -> 0.49265662 | D13: =Raw_Data!E6 / SUM(Raw_Data!E$4:E$6) -> 0.37330867
B15: Net Margin | C15: =Raw_Data!D7 / Raw_Data!D3 -> 0.41736528 | D15: =Raw_Data!E7 / Raw_Data!E3 -> 0.26388717
B17: Marketplace Bridge
B18: Marketplace Revenue (KZ Organic) | C18: =Raw_Data!D5 -> 732943 | D18: =Raw_Data!E5 - Raw_Data!E17 -> 936118 | E18: =(D18/C18)-1 -> 0.27720437
B19: Share of Growth from Hepsiburada | D19: =Raw_Data!E17 / (Raw_Data!E5 - Raw_Data!D5) -> 0.8304797
B21: Kazakhstan Standalone
B22: Payments Take Rate | C22: =Raw_Data!D4 / Raw_Data!D9 -> 0.015769884 | D22: =Raw_Data!E4 / Raw_Data!E9 -> 0.0148969
B23: Marketplace Monetization | C23: =Raw_Data!D5 / Raw_Data!D10 -> 0.12266828 | D23: =(Raw_Data!E5 - Raw_Data!E17) / Raw_Data!E10 -> 0.1406216
B24: GMV per Active Consumer | C24: =Raw_Data!D10 / Raw_Data!D14 -> 737654.32 | D24: =Raw_Data!E10 / Raw_Data!E14 -> 756477.27
B25: Fintech TFV Yield | C25: =Raw_Data!D6 / Raw_Data!D11 -> 0.12438884 | D25: =Raw_Data!E6 / Raw_Data!E11 -> 0.13241795
B26: Payments ARPU | C26: =Raw_Data!D4 / Raw_Data!D13 -> 43168.897 | D26: =Raw_Data!E4 / Raw_Data!E13 -> 45118.219
B27: Marketplace Organic ARPU | C27: =C18 / Raw_Data!D14 -> 90486.79 | D27: =D18 / Raw_Data!E14 -> 106377.05
B28: Fintech ARPU | C28: =Raw_Data!D6 / Raw_Data!D15 -> 200285.47 | D28: =Raw_Data!E6 / Raw_Data!E15 -> 244910.16
B30: 2026E Scenario Analysis (KZ) | C30: Bear Case | D30: Base Case | E30: Bull Case | I30: Category | J30: 2025 KZ Organic | K30: Hepsiburada / Türkiye
B31: Payments TPV Growth | C31: 0.1 | D31: 0.15 | E31: 0.2 | I31: 2024 Marketplace | J31: 732943 | K31: 0
B32: Payments Take Rate | C32: 0.0145 | D32: 0.0149 | E32: 0.0152 | I32: 2025 Marketplace | J32: 936118 | K32: 995354
B33: Marketplace GMV Growth | C33: 0.08 | D33: 0.12 | E33: 0.18
B34: Marketplace Monetization | C34: 0.135 | D34: 0.145 | E34: 0.155 | I34: Year | J34: Revenue (Billion) | K34: Net Margin (%)
B35: Fintech TFV Growth | C35: 0.08 | D35: 0.13 | E35: 0.18 | I35: 2024 | J35: 2532156 | K35: 0.417
B36: Fintech TFV Yield | C36: 0.128 | D36: 0.132 | E36: 0.136 | I36: 2025 | J36: 4046074 | K36: 0.264
B37: 2026E Payments Revenue | C37: =Raw_Data!$E9*(1+C31)*C32 -> 705293.05 | D37: =Raw_Data!$E9*(1+D31)*D32 -> 757692.56 | E37: =Raw_Data!$E9*(1+E31)*E32 -> 806554.56
B38: 2026E Marketplace Rev (KZ) | C38: =Raw_Data!$E10*(1+C33)*C34 -> 970590.6 | D38: =Raw_Data!$E10*(1+D33)*D34 -> 1081096.8 | E38: =Raw_Data!$E10*(1+E33)*E34 -> 1217565.3
B39: 2026E Fintech Revenue | C39: =Raw_Data!$E11*(1+C35)*C36 -> 1610772.5 | D39: =Raw_Data!$E11*(1+D35)*D36 -> 1738012.3 | E39: =Raw_Data!$E11*(1+E35)*E36 -> 1869913
B40: Total 2026E KZ Revenue | C40: =SUM(C37:C39) -> 3286656.1 | D40: =SUM(D37:D39) -> 3576801.7 | E40: =SUM(E37:E39) -> 3894032.8

Sheet Dashboard
